LICENSE
MANIFEST.in
README.md
requirements.txt
setup.cfg
setup.py
django_payeer.egg-info/PKG-INFO
django_payeer.egg-info/SOURCES.txt
django_payeer.egg-info/dependency_links.txt
django_payeer.egg-info/top_level.txt
payeer/__init__.py
payeer/api.py
payeer/constants.py
payeer/forms.py
payeer/settings.py