Metadata-Version: 1.1
Name: django-payeer
Version: 0.2
Summary: Django payeer app
Home-page: https://github.com/pmaigutyak/mp-payeer
Author: Paul Maigutyak
Author-email: pmaigutyak@gmail.com
License: MIT
Download-URL: https://github.com/pmaigutyak/mp-payeer/archive/0.2.tar.gz
Platform: UNKNOWN
